databeaver/__init__.py
databeaver/data/configSample.ini
databeaver/data/configSample.json
databeaver/data/configSample.toml
databeaver/lib/DataBeaver.py
databeaver/lib/DataStorage.py
databeaver/lib/MySQL.py
databeaver/lib/Object.py
databeaver/lib/PostgreSQL.py
databeaver/lib/Schema.py
databeaver/lib/System.py
databeaver/lib/Table.py
databeaver/lib/__init__.py
databeaver/lib/constants.py
databeaver-0.2.11.data/scripts/beaver
databeaver-0.2.11.dist-info/LICENSE
databeaver-0.2.11.dist-info/METADATA
databeaver-0.2.11.dist-info/WHEEL
databeaver-0.2.11.dist-info/top_level.txt
databeaver-0.2.11.dist-info/RECORD
