Metadata-Version: 2.1
Name: databeaver
Version: 0.2.11
Summary: Data Model Orchestration
Home-page: https://opensource.fuzzybumblebee.org/databeaver/latest
Author: Fuzzy Bumblebee Software, LLC
Author-email: david.orkin@fuzzybumblebee.org
Project-URL: Bug Tracker, https://github.com/FBB-David/databeaver/issues
Classifier: Programming Language :: Python :: 3
Classifier: License :: OSI Approved :: GNU Lesser General Public License v3 (LGPLv3)
Classifier: Operating System :: POSIX :: Linux
Requires-Python: >=3.6
License-File: LICENSE
Requires-Dist: tomli
